koronavirus/__init__.py
koronavirus/koronavirus.py
koronavirus-1.0.0.dist-info/LICENSE.txt
koronavirus-1.0.0.dist-info/METADATA
koronavirus-1.0.0.dist-info/WHEEL
koronavirus-1.0.0.dist-info/top_level.txt
koronavirus-1.0.0.dist-info/RECORD
